NiukeQianduanGongchengshiQiuzhiJingyanFenxiang20212022Fix1/README.md
NiukeQianduanGongchengshiQiuzhiJingyanFenxiang20212022Fix1/__init__.py
NiukeQianduanGongchengshiQiuzhiJingyanFenxiang20212022Fix1/__main__.py
NiukeQianduanGongchengshiQiuzhiJingyanFenxiang20212022Fix1/file.epub
NiukeQianduanGongchengshiQiuzhiJingyanFenxiang20212022Fix1/index.html
NiukeQianduanGongchengshiQiuzhiJingyanFenxiang20212022Fix1/css/__init__.py
NiukeQianduanGongchengshiQiuzhiJingyanFenxiang20212022Fix1/css/annotations.css
NiukeQianduanGongchengshiQiuzhiJingyanFenxiang20212022Fix1/css/main.css
NiukeQianduanGongchengshiQiuzhiJingyanFenxiang20212022Fix1/css/normalize.css
NiukeQianduanGongchengshiQiuzhiJingyanFenxiang20212022Fix1/css/popup.css
NiukeQianduanGongchengshiQiuzhiJingyanFenxiang20212022Fix1/font/__init__.py
NiukeQianduanGongchengshiQiuzhiJingyanFenxiang20212022Fix1/font/fontello.eot
NiukeQianduanGongchengshiQiuzhiJingyanFenxiang20212022Fix1/font/fontello.svg
NiukeQianduanGongchengshiQiuzhiJingyanFenxiang20212022Fix1/font/fontello.ttf
NiukeQianduanGongchengshiQiuzhiJingyanFenxiang20212022Fix1/font/fontello.woff
NiukeQianduanGongchengshiQiuzhiJingyanFenxiang20212022Fix1/img/__init__.py
NiukeQianduanGongchengshiQiuzhiJingyanFenxiang20212022Fix1/img/annotator-glyph-sprite.png
NiukeQianduanGongchengshiQiuzhiJingyanFenxiang20212022Fix1/img/annotator-icon-sprite.png
NiukeQianduanGongchengshiQiuzhiJingyanFenxiang20212022Fix1/img/apple-touch-icon.png
NiukeQianduanGongchengshiQiuzhiJingyanFenxiang20212022Fix1/img/cancelfullscreen.png
NiukeQianduanGongchengshiQiuzhiJingyanFenxiang20212022Fix1/img/close.png
NiukeQianduanGongchengshiQiuzhiJingyanFenxiang20212022Fix1/img/fullscreen.png
NiukeQianduanGongchengshiQiuzhiJingyanFenxiang20212022Fix1/img/loader.gif
NiukeQianduanGongchengshiQiuzhiJingyanFenxiang20212022Fix1/img/menu-icon.png
NiukeQianduanGongchengshiQiuzhiJingyanFenxiang20212022Fix1/img/save.png
NiukeQianduanGongchengshiQiuzhiJingyanFenxiang20212022Fix1/img/saved.png
niuke_qianduan_gongchengshi_qiuzhi_jingyan_fenxiang_2021_2022_fix1-2025.3.25.0.dist-info/METADATA
niuke_qianduan_gongchengshi_qiuzhi_jingyan_fenxiang_2021_2022_fix1-2025.3.25.0.dist-info/WHEEL
niuke_qianduan_gongchengshi_qiuzhi_jingyan_fenxiang_2021_2022_fix1-2025.3.25.0.dist-info/entry_points.txt
niuke_qianduan_gongchengshi_qiuzhi_jingyan_fenxiang_2021_2022_fix1-2025.3.25.0.dist-info/top_level.txt
niuke_qianduan_gongchengshi_qiuzhi_jingyan_fenxiang_2021_2022_fix1-2025.3.25.0.dist-info/RECORD
